chatfaq_sdk/__init__.py
chatfaq_sdk/agents/__init__.py
chatfaq_sdk/clients/__init__.py
chatfaq_sdk/clients/agent.py
chatfaq_sdk/conditions/__init__.py
chatfaq_sdk/data_source_parsers/__init__.py
chatfaq_sdk/fsm/__init__.py
chatfaq_sdk/layers/__init__.py
chatfaq_sdk/settings.py
chatfaq_sdk/types/__init__.py
chatfaq_sdk/types/messages.py
chatfaq_sdk/utils.py
chatfaq_sdk-0.1.57.dist-info/METADATA
chatfaq_sdk-0.1.57.dist-info/WHEEL
chatfaq_sdk-0.1.57.dist-info/RECORD
