Metadata-Version: 2.3
Name: chatfaq_sdk
Version: 0.1.57
Summary: ChatFAQ SDK
Author: Hector Soria
Author-email: hector.soria@with-madrid.com
Requires-Python: >=3.10,<4.0
Classifier: Programming Language :: Python :: 3
Classifier: Programming Language :: Python :: 3.10
Classifier: Programming Language :: Python :: 3.11
Classifier: Programming Language :: Python :: 3.12
Classifier: Programming Language :: Python :: 3.13
Requires-Dist: asyncio (>=3.4.3,<4.0.0)
Requires-Dist: certifi (>=2025.8.3,<2026.0.0)
Requires-Dist: coloredlogs (>=15.0.1,<16.0.0)
Requires-Dist: httpx (>=0.28.1,<0.29.0)
Requires-Dist: pydantic (>=2.8.2,<3.0.0)
Requires-Dist: python-dotenv (>=1.0.0,<2.0.0)
Requires-Dist: requests (>=2.31.0,<3.0.0)
Requires-Dist: sentry-sdk (>=2.15.0,<3.0.0)
Requires-Dist: urllib3 (>=2.5.0,<3.0.0)
Requires-Dist: websockets (>=15.0.1,<16.0.0)
